messagemap/__init__.py
messagemap/functions.py
messagemap-0.0.2.dist-info/LICENSE
messagemap-0.0.2.dist-info/METADATA
messagemap-0.0.2.dist-info/WHEEL
messagemap-0.0.2.dist-info/top_level.txt
messagemap-0.0.2.dist-info/RECORD
