Metadata-Version: 2.1
Name: messagemap
Version: 0.0.2
Summary: MessageMap.IO Interface to API of deployed Environment
Home-page: https://github.com/MessageMap/py-messagemap
Author: Ben Adams
Author-email: ben@messagemap.io
License: MIT
Download-URL: https://pypi.org/project/messagemap/
Keywords: Message Queue,Messages
Platform: UNKNOWN
Classifier: Programming Language :: Python :: 3
Classifier: Operating System :: OS Independent
Requires-Python: >=3.6
License-File: LICENSE
Requires-Dist: requests
